certbot_dns_websupport/__init__.py
certbot_dns_websupport/_internal/__init__.py
certbot_dns_websupport/_internal/dns_websupport.py
certbot_dns_websupport-3.0.0.dist-info/LICENSE
certbot_dns_websupport-3.0.0.dist-info/METADATA
certbot_dns_websupport-3.0.0.dist-info/WHEEL
certbot_dns_websupport-3.0.0.dist-info/entry_points.txt
certbot_dns_websupport-3.0.0.dist-info/RECORD
